inpystem/__init__.py
inpystem/dataset.py
inpystem/dev.py
inpystem/logger.py
inpystem/signals.py
inpystem/version.py
inpystem/restore/DL_BPFA.py
inpystem/restore/DL_ITKrMM.py
inpystem/restore/DL_ITKrMM_matlab.py
inpystem/restore/LS_2D.py
inpystem/restore/LS_3D.py
inpystem/restore/LS_CLS.py
inpystem/restore/__init__.py
inpystem/restore/interpolation.py
inpystem/restore/MatlabCodes/sec2str.m
inpystem/restore/MatlabCodes/BPFA/BPFA.m
inpystem/restore/MatlabCodes/BPFA/BPFA_GP.m
inpystem/restore/MatlabCodes/BPFA/BPFA_for_python.m
inpystem/restore/MatlabCodes/BPFA/CovMatrix.m
inpystem/restore/MatlabCodes/BPFA/Demo.m
inpystem/restore/MatlabCodes/BPFA/GP_Predict.m
inpystem/restore/MatlabCodes/BPFA/InpaintingOutput.m
inpystem/restore/MatlabCodes/BPFA/MissingBand.m
inpystem/restore/MatlabCodes/BPFA/Readme.txt
inpystem/restore/MatlabCodes/BPFA/VectorizePatch.m
inpystem/restore/MatlabCodes/BPFA/blockchol.m
inpystem/restore/MatlabCodes/BPFA/blockinv.m
inpystem/restore/MatlabCodes/BPFA/par_BPFA_GP.m
inpystem/restore/MatlabCodes/BPFA/sparse_mult.m
inpystem/restore/MatlabCodes/ITKrMM/.DS_Store
inpystem/restore/MatlabCodes/ITKrMM/ITKrMM_CLS_init_for_python.m
inpystem/restore/MatlabCodes/ITKrMM/ITKrMM_for_python.m
inpystem/restore/MatlabCodes/ITKrMM/OMPm.m
inpystem/restore/MatlabCodes/ITKrMM/RandMask.m
inpystem/restore/MatlabCodes/ITKrMM/inpainting_script.m
inpystem/restore/MatlabCodes/ITKrMM/itkrm.m
inpystem/restore/MatlabCodes/ITKrMM/itkrmm.m
inpystem/restore/MatlabCodes/ITKrMM/makesparselowsig.m
inpystem/restore/MatlabCodes/ITKrMM/maskTimeVar.m
inpystem/restore/MatlabCodes/ITKrMM/patches2pic.m
inpystem/restore/MatlabCodes/ITKrMM/pic2patches.m
inpystem/restore/MatlabCodes/ITKrMM/readme.txt
inpystem/restore/MatlabCodes/ITKrMM/rec_lratom.m
inpystem/restore/MatlabCodes/ITKrMM/showdico.m
inpystem/restore/MatlabCodes/ITKrMM/test_script.m
inpystem/restore/MatlabCodes/ITKrMM/wKSVD.m
inpystem/restore/MatlabCodes/ITKrMM/wKSVD_for_python.m
inpystem-0.1.1.dist-info/LICENSE
inpystem-0.1.1.dist-info/METADATA
inpystem-0.1.1.dist-info/WHEEL
inpystem-0.1.1.dist-info/top_level.txt
inpystem-0.1.1.dist-info/RECORD
