Metadata-Version: 2.1
Name: inpystem
Version: 0.1.1
Summary: A python library for STEM acquisition inpainting.
Home-page: https://github.com/etienne-monier/inpystem
Author: Etienne Monier
Author-email: etienne.monier@enseeiht.fr
License: MIT
Project-URL: Source Code, https://github.com/etienne-monier/inpystem
Project-URL: Documentation, https://inpystem.readthedocs.io/en/latest/index.html
Keywords: STEM,dm3,electron energy loss spectroscopy,electron microscopy,hyperspectral,hyperspectrum,multidimensional,hyperspy,microscopy,numpy,python,scipy,spectrum image,reconstruction,sinal processing
Platform: Linux
Classifier: Programming Language :: Python :: 3
Classifier: License :: OSI Approved :: MIT License
Classifier: Operating System :: OS Independent
Classifier: Intended Audience :: Science/Research
Classifier: Topic :: Scientific/Engineering
Classifier: Natural Language :: English
Requires-Python: >=3.6
Requires-Dist: numpy
Requires-Dist: scipy
Requires-Dist: matplotlib
Requires-Dist: hyperspy
Requires-Dist: scikit-learn
Requires-Dist: scikit-image (>=0.16)
